sotodlib/__init__.py
sotodlib/_version.py
sotodlib/flag_utils.py
sotodlib/g3_condition.py
sotodlib/g3_filter.py
sotodlib/g3_sim.py
sotodlib/sim_flags.py
sotodlib/sim_hardware.py
sotodlib/vis_hardware.py
sotodlib/coords/__init__.py
sotodlib/coords/demod.py
sotodlib/coords/det_match.py
sotodlib/coords/fp_containers.py
sotodlib/coords/healpix_utils.py
sotodlib/coords/helpers.py
sotodlib/coords/local.py
sotodlib/coords/optics.py
sotodlib/coords/planets.py
sotodlib/coords/plotting.py
sotodlib/coords/pmat.py
sotodlib/coords/pointing_model.py
sotodlib/core/__init__.py
sotodlib/core/axisman.py
sotodlib/core/axisman_io.py
sotodlib/core/axisman_util.py
sotodlib/core/context.py
sotodlib/core/flagman.py
sotodlib/core/g3_core.py
sotodlib/core/hardware.py
sotodlib/core/resources.py
sotodlib/core/util.py
sotodlib/core/metadata/__init__.py
sotodlib/core/metadata/cli.py
sotodlib/core/metadata/common.py
sotodlib/core/metadata/detdb.py
sotodlib/core/metadata/loader.py
sotodlib/core/metadata/manifest.py
sotodlib/core/metadata/obsdb.py
sotodlib/core/metadata/obsfiledb.py
sotodlib/core/metadata/resultset.py
sotodlib/hwp/__init__.py
sotodlib/hwp/g3thwp.py
sotodlib/hwp/hwp.py
sotodlib/hwp/hwp_angle_model.py
sotodlib/hwp/sim_hwp.py
sotodlib/io/__init__.py
sotodlib/io/bookbinder.py
sotodlib/io/check_book.py
sotodlib/io/datapkg_completion.py
sotodlib/io/datapkg_utils.py
sotodlib/io/g3thk_db.py
sotodlib/io/g3thk_utils.py
sotodlib/io/g3tsmurf_db.py
sotodlib/io/g3tsmurf_utils.py
sotodlib/io/hk_utils.py
sotodlib/io/hkdb.py
sotodlib/io/imprinter.py
sotodlib/io/imprinter_cli.py
sotodlib/io/imprinter_utils.py
sotodlib/io/load.py
sotodlib/io/load_book.py
sotodlib/io/load_smurf.py
sotodlib/io/load_toast_h5.py
sotodlib/io/metadata.py
sotodlib/io/so_ufm.py
sotodlib/mapmaking/__init__.py
sotodlib/mapmaking/bench.py
sotodlib/mapmaking/coadd_mapmaker.py
sotodlib/mapmaking/demod_mapmaker.py
sotodlib/mapmaking/log.py
sotodlib/mapmaking/ml_mapmaker.py
sotodlib/mapmaking/noise_model.py
sotodlib-0.6.16.dist-info/licenses/LICENSE
sotodlib-0.6.16.dist-info/METADATA
sotodlib-0.6.16.dist-info/WHEEL
sotodlib-0.6.16.dist-info/entry_points.txt
sotodlib-0.6.16.dist-info/top_level.txt
sotodlib-0.6.16.dist-info/RECORD
