Metadata-Version: 2.4
Name: sotodlib
Version: 0.6.16
Summary: Simons Observatory TOD Simulation and Processing
Maintainer: Simons Observatory Collaboration
Maintainer-email: so_software@simonsobservatory.org
License-Expression: MIT
Project-URL: Source, https://github.com/simonsobs/sotodlib
Project-URL: Issue Tracker, https://github.com/simonsobs/sotodlib/issues
Classifier: Development Status :: 4 - Beta
Classifier: Environment :: Console
Classifier: Intended Audience :: Science/Research
Classifier: Topic :: Scientific/Engineering :: Astronomy
Classifier: Programming Language :: Python :: 3.10
Classifier: Programming Language :: Python :: 3.11
Classifier: Programming Language :: Python :: 3.12
Classifier: Programming Language :: Python :: 3.13
Requires-Python: <3.14,>=3.10
License-File: LICENSE
Requires-Dist: numpy
Requires-Dist: scipy
Requires-Dist: matplotlib
Requires-Dist: quaternionarray
Requires-Dist: PyYAML
Requires-Dist: toml
Requires-Dist: skyfield
Requires-Dist: so3g
Requires-Dist: pixell>=0.23.0
Requires-Dist: pytest
Requires-Dist: scikit-image
Requires-Dist: pyfftw
Requires-Dist: numdifftools
Requires-Dist: psycopg2-binary
Requires-Dist: lmfit
Requires-Dist: flacarray>=0.3.4
Requires-Dist: h5py
Provides-Extra: site-pipeline
Requires-Dist: influxdb; extra == "site-pipeline"
Requires-Dist: venn; extra == "site-pipeline"
Requires-Dist: let-me-scroll-it; extra == "site-pipeline"
Requires-Dist: plotly; extra == "site-pipeline"
Requires-Dist: pandas; extra == "site-pipeline"
Requires-Dist: alphashape; extra == "site-pipeline"
Requires-Dist: slack-sdk; extra == "site-pipeline"
Requires-Dist: requests; extra == "site-pipeline"
Provides-Extra: tests
Requires-Dist: socs; extra == "tests"
Dynamic: license-file
